pyhanko_beid/__init__.py
pyhanko_beid/beid.py
pyhanko_beid/cli.py
pyhanko_beid/py.typed
pyhanko_beid_plugin-0.2.0.dist-info/licenses/LICENSE
pyhanko_beid_plugin-0.2.0.dist-info/METADATA
pyhanko_beid_plugin-0.2.0.dist-info/WHEEL
pyhanko_beid_plugin-0.2.0.dist-info/entry_points.txt
pyhanko_beid_plugin-0.2.0.dist-info/top_level.txt
pyhanko_beid_plugin-0.2.0.dist-info/RECORD
