Metadata-Version: 2.4
Name: pyhanko-beid-plugin
Version: 0.2.0
Summary: pyHanko plugin for Belgian ID cards
Author-email: Matthias Valvekens <dev@mvalvekens.be>
Maintainer-email: Matthias Valvekens <dev@mvalvekens.be>
License: MIT
Project-URL: Homepage, https://github.com/MatthiasValvekens/pyhanko-beid-plugin
Project-URL: Source Code, https://github.com/MatthiasValvekens/pyhanko-beid-plugin
Project-URL: Issue Tracker, https://github.com/MatthiasValvekens/pyHanko/issues
Keywords: signature,pdf,digital-signature,pkcs11
Classifier: Development Status :: 4 - Beta
Classifier: Intended Audience :: Information Technology
Classifier: Intended Audience :: Developers
Classifier: Operating System :: OS Independent
Classifier: License :: OSI Approved :: MIT License
Classifier: Programming Language :: Python :: 3
Classifier: Programming Language :: Python :: 3.9
Classifier: Programming Language :: Python :: 3.10
Classifier: Programming Language :: Python :: 3.11
Classifier: Programming Language :: Python :: 3.12
Classifier: Programming Language :: Python :: 3.13
Classifier: Topic :: Security :: Cryptography
Classifier: Topic :: Software Development :: Libraries :: Python Modules
Requires-Python: >=3.9
License-File: LICENSE
Requires-Dist: pyHanko[pkcs11]>=0.29.0
Requires-Dist: pyhanko-cli>=0.1.1
Provides-Extra: testing
Requires-Dist: pyhanko-beid-plugin; extra == "testing"
Requires-Dist: pytest>=6.1.1; extra == "testing"
Requires-Dist: pytest-cov<6.2,>=4.0; extra == "testing"
Provides-Extra: mypy
Requires-Dist: pyhanko-beid-plugin; extra == "mypy"
Requires-Dist: types-PyYAML; extra == "mypy"
Dynamic: license-file
